{
  "ibs-records": [
    {
      "type": "food_log",
      "timestamp": "2026-02-01T08:10:00.000Z",
      "text": "Porridge mit Banane",
      "tags": ["Haferflocken", "Banane", "Zimt"],
      "size": 2,
      "speed": 2,
      "risk": 1
    },
    {
      "type": "symptoms",
      "timestamp": "2026-02-01T11:45:00.000Z",
      "pain": 0,
      "bloating": 1
    },
    {
      "type": "bm",
      "timestamp": "2026-02-01T12:30:00.000Z",
      "bristol-scale": 4,
      "evacuation": "full",
      "pressure": 1,
      "wetness": 1,
      "tags": []
    },
    {
      "type": "food_log",
      "timestamp": "2026-02-02T12:20:00.000Z",
      "text": "Reis mit Huhn",
      "tags": ["Reis", "Huhn", "Karotten"],
      "size": 3,
      "speed": 2,
      "risk": 1
    },
    {
      "type": "bm",
      "timestamp": "2026-02-02T18:10:00.000Z",
      "bristol-scale": 4,
      "evacuation": "full",
      "pressure": 1,
      "wetness": 1,
      "tags": []
    },
    {
      "type": "food_log",
      "timestamp": "2026-02-03T07:50:00.000Z",
      "text": "Kaffee und Croissant",
      "tags": ["Kaffee", "Croissant"],
      "size": 2,
      "speed": 3,
      "risk": 3
    },
    {
      "type": "symptoms",
      "timestamp": "2026-02-03T10:40:00.000Z",
      "pain": 2,
      "bloating": 3
    },
    {
      "type": "bm",
      "timestamp": "2026-02-03T11:20:00.000Z",
      "bristol-scale": 6,
      "evacuation": "partial",
      "pressure": 2,
      "wetness": 3,
      "tags": []
    },
    {
      "type": "bm",
      "timestamp": "2026-02-03T16:10:00.000Z",
      "bristol-scale": 5,
      "evacuation": "partial",
      "pressure": 2,
      "wetness": 2,
      "tags": []
    },
    {
      "type": "food_log",
      "timestamp": "2026-02-04T13:00:00.000Z",
      "text": "Reis mit Huhn",
      "tags": ["Reis", "Huhn", "Karotten"],
      "size": 3,
      "speed": 2,
      "risk": 1
    },
    {
      "type": "symptoms",
      "timestamp": "2026-02-04T20:15:00.000Z",
      "pain": 0,
      "bloating": 0
    },
    {
      "type": "food_log",
      "timestamp": "2026-02-05T18:30:00.000Z",
      "text": "Pizza Salami",
      "tags": ["Pizza", "Käse", "Salami"],
      "size": 4,
      "speed": 3,
      "risk": 4
    },
    {
      "type": "symptoms",
      "timestamp": "2026-02-05T22:00:00.000Z",
      "pain": 4,
      "bloating": 4
    },
    {
      "type": "bm",
      "timestamp": "2026-02-06T07:45:00.000Z",
      "bristol-scale": 6,
      "evacuation": "partial",
      "pressure": 3,
      "wetness": 3,
      "tags": []
    },
    {
      "type": "bm",
      "timestamp": "2026-02-06T09:10:00.000Z",
      "bristol-scale": 6,
      "evacuation": "partial",
      "pressure": 3,
      "wetness": 3,
      "tags": []
    },
    {
      "type": "food_log",
      "timestamp": "2026-02-07T09:15:00.000Z",
      "text": "Porridge mit Banane",
      "tags": ["Haferflocken", "Banane", "Zimt"],
      "size": 2,
      "speed": 1,
      "risk": 1
    },
    {
      "type": "symptoms",
      "timestamp": "2026-02-07T13:20:00.000Z",
      "pain": 0,
      "bloating": 1
    },
    {
      "type": "food_log",
      "timestamp": "2026-02-09T12:00:00.000Z",
      "text": "Sushi Bowl",
      "tags": ["Reis", "Lachs", "Gurke"],
      "size": 3,
      "speed": 2,
      "risk": 2
    },
    {
      "type": "bm",
      "timestamp": "2026-02-09T17:40:00.000Z",
      "bristol-scale": 4,
      "evacuation": "full",
      "pressure": 1,
      "wetness": 1,
      "tags": []
    },
    {
      "type": "food_log",
      "timestamp": "2026-02-10T08:05:00.000Z",
      "text": "Kaffee und Croissant",
      "tags": ["Kaffee", "Croissant"],
      "size": 2,
      "speed": 2,
      "risk": 3
    },
    {
      "type": "symptoms",
      "timestamp": "2026-02-10T10:30:00.000Z",
      "pain": 1,
      "bloating": 2
    },
    {
      "type": "food_log",
      "timestamp": "2026-02-11T19:10:00.000Z",
      "text": "Burger mit Pommes",
      "tags": ["Burger", "Pommes", "Ketchup"],
      "size": 4,
      "speed": 4,
      "risk": 5
    },
    {
      "type": "symptoms",
      "timestamp": "2026-02-11T22:30:00.000Z",
      "pain": 5,
      "bloating": 4
    },
    {
      "type": "bm",
      "timestamp": "2026-02-12T06:50:00.000Z",
      "bristol-scale": 7,
      "evacuation": "partial",
      "pressure": 4,
      "wetness": 4,
      "tags": []
    },
    {
      "type": "bm",
      "timestamp": "2026-02-12T08:00:00.000Z",
      "bristol-scale": 6,
      "evacuation": "partial",
      "pressure": 3,
      "wetness": 4,
      "tags": []
    },
    {
      "type": "bm",
      "timestamp": "2026-02-12T11:15:00.000Z",
      "bristol-scale": 5,
      "evacuation": "partial",
      "pressure": 2,
      "wetness": 2,
      "tags": []
    },
    {
      "type": "food_log",
      "timestamp": "2026-02-13T12:30:00.000Z",
      "text": "Reis mit Huhn",
      "tags": ["Reis", "Huhn", "Karotten"],
      "size": 3,
      "speed": 2,
      "risk": 1
    },
    {
      "type": "symptoms",
      "timestamp": "2026-02-13T21:10:00.000Z",
      "pain": 0,
      "bloating": 0
    },
    {
      "type": "food_log",
      "timestamp": "2026-02-14T18:45:00.000Z",
      "text": "Pizza Salami",
      "tags": ["Pizza", "Käse", "Salami"],
      "size": 4,
      "speed": 3,
      "risk": 4
    },
    {
      "type": "symptoms",
      "timestamp": "2026-02-14T22:20:00.000Z",
      "pain": 3,
      "bloating": 3
    },
    {
      "type": "bm",
      "timestamp": "2026-02-15T09:35:00.000Z",
      "bristol-scale": 5,
      "evacuation": "full",
      "pressure": 2,
      "wetness": 2,
      "tags": []
    },
    {
      "type": "food_log",
      "timestamp": "2026-02-16T07:40:00.000Z",
      "text": "Porridge mit Banane",
      "tags": ["Haferflocken", "Banane", "Zimt"],
      "size": 2,
      "speed": 1,
      "risk": 1
    },
    {
      "type": "food_log",
      "timestamp": "2026-02-17T12:05:00.000Z",
      "text": "Sushi Bowl",
      "tags": ["Reis", "Lachs", "Gurke"],
      "size": 3,
      "speed": 2,
      "risk": 2
    },
    {
      "type": "symptoms",
      "timestamp": "2026-02-17T20:00:00.000Z",
      "pain": 1,
      "bloating": 1
    },
    {
      "type": "food_log",
      "timestamp": "2026-02-18T20:10:00.000Z",
      "text": "Burger mit Pommes",
      "tags": ["Burger", "Pommes", "Ketchup"],
      "size": 4,
      "speed": 4,
      "risk": 5
    },
    {
      "type": "symptoms",
      "timestamp": "2026-02-18T23:10:00.000Z",
      "pain": 4,
      "bloating": 4
    },
    {
      "type": "bm",
      "timestamp": "2026-02-19T07:20:00.000Z",
      "bristol-scale": 6,
      "evacuation": "partial",
      "pressure": 3,
      "wetness": 3,
      "tags": []
    },
    {
      "type": "bm",
      "timestamp": "2026-02-19T08:25:00.000Z",
      "bristol-scale": 5,
      "evacuation": "partial",
      "pressure": 2,
      "wetness": 2,
      "tags": []
    },
    {
      "type": "food_log",
      "timestamp": "2026-02-20T12:20:00.000Z",
      "text": "Reis mit Huhn",
      "tags": ["Reis", "Huhn", "Karotten"],
      "size": 3,
      "speed": 2,
      "risk": 1
    },
    {
      "type": "symptoms",
      "timestamp": "2026-02-20T21:00:00.000Z",
      "pain": 0,
      "bloating": 0
    },
    {
      "type": "food_log",
      "timestamp": "2026-02-21T09:10:00.000Z",
      "text": "Kaffee und Croissant",
      "tags": ["Kaffee", "Croissant"],
      "size": 2,
      "speed": 2,
      "risk": 3
    },
    {
      "type": "bm",
      "timestamp": "2026-02-21T10:05:00.000Z",
      "bristol-scale": 4,
      "evacuation": "full",
      "pressure": 1,
      "wetness": 1,
      "tags": []
    },
    {
      "type": "food_log",
      "timestamp": "2026-02-22T18:55:00.000Z",
      "text": "Pizza Salami",
      "tags": ["Pizza", "Käse", "Salami"],
      "size": 4,
      "speed": 3,
      "risk": 4
    },
    {
      "type": "symptoms",
      "timestamp": "2026-02-22T22:45:00.000Z",
      "pain": 3,
      "bloating": 3
    },
    {
      "type": "food_log",
      "timestamp": "2026-02-24T12:10:00.000Z",
      "text": "Sushi Bowl",
      "tags": ["Reis", "Lachs", "Gurke"],
      "size": 3,
      "speed": 2,
      "risk": 2
    },
    {
      "type": "symptoms",
      "timestamp": "2026-02-24T20:40:00.000Z",
      "pain": 0,
      "bloating": 1
    },
    {
      "type": "bm",
      "timestamp": "2026-02-25T07:55:00.000Z",
      "bristol-scale": 4,
      "evacuation": "full",
      "pressure": 1,
      "wetness": 1,
      "tags": []
    },
    {
      "type": "food_log",
      "timestamp": "2026-02-26T19:00:00.000Z",
      "text": "Burger mit Pommes",
      "tags": ["Burger", "Pommes", "Ketchup"],
      "size": 4,
      "speed": 4,
      "risk": 5
    },
    {
      "type": "symptoms",
      "timestamp": "2026-02-26T22:50:00.000Z",
      "pain": 4,
      "bloating": 4
    },
    {
      "type": "bm",
      "timestamp": "2026-02-27T06:40:00.000Z",
      "bristol-scale": 6,
      "evacuation": "partial",
      "pressure": 3,
      "wetness": 3,
      "tags": []
    },
    {
      "type": "bm",
      "timestamp": "2026-02-27T07:30:00.000Z",
      "bristol-scale": 6,
      "evacuation": "partial",
      "pressure": 3,
      "wetness": 3,
      "tags": []
    },
    {
      "type": "food_log",
      "timestamp": "2026-02-28T09:00:00.000Z",
      "text": "Porridge mit Banane",
      "tags": ["Haferflocken", "Banane", "Zimt"],
      "size": 2,
      "speed": 1,
      "risk": 1
    },
    {
      "type": "symptoms",
      "timestamp": "2026-02-28T20:15:00.000Z",
      "pain": 0,
      "bloating": 0
    }
  ]
}
